wdcsdcsd123456/__init__.py
wdcsdcsd123456/nestList.py
wdcsdcsd123456-0.0.1.dist-info/LICENSE
wdcsdcsd123456-0.0.1.dist-info/METADATA
wdcsdcsd123456-0.0.1.dist-info/WHEEL
wdcsdcsd123456-0.0.1.dist-info/top_level.txt
wdcsdcsd123456-0.0.1.dist-info/RECORD
