Metadata-Version: 2.1
Name: wdcsdcsd123456
Version: 0.0.1
Summary: A small example package
Home-page: https://github.com/PepperPapa/xinNotes
Author: Example Author
Author-email: author@example.com
License: UNKNOWN
Platform: UNKNOWN
Classifier: Programming Language :: Python :: 3
Classifier: License :: OSI Approved :: MIT License
Classifier: Operating System :: OS Independent
